traceback_assistant/__init__.py
traceback_assistant/assistant.py
traceback_assistant-0.1.0.dist-info/licenses/LICENSE
traceback_assistant-0.1.0.dist-info/METADATA
traceback_assistant-0.1.0.dist-info/WHEEL
traceback_assistant-0.1.0.dist-info/entry_points.txt
traceback_assistant-0.1.0.dist-info/top_level.txt
traceback_assistant-0.1.0.dist-info/RECORD
