Metadata-Version: 2.4
Name: traceback_assistant
Version: 0.1.0
Summary: A package to explain Python tracebacks using OpenAI.
Home-page: https://github.com/yourusername/traceback_assistant
Author: Your Name
Author-email: your.email@example.com
Classifier: Programming Language :: Python :: 3
Classifier: License :: OSI Approved :: MIT License
Classifier: Operating System :: OS Independent
Requires-Python: >=3.6
License-File: LICENSE
Requires-Dist: openai==0.27.8
Requires-Dist: pytest==7.4.2
Requires-Dist: setuptools
Requires-Dist: wheel
Requires-Dist: twine
Dynamic: author
Dynamic: author-email
Dynamic: classifier
Dynamic: description
Dynamic: description-content-type
Dynamic: home-page
Dynamic: license-file
Dynamic: requires-dist
Dynamic: requires-python
Dynamic: summary
